README.rst
setup.py
dumpy/__init__.py
dumpy/config.py
dumpy/types.py
dumpy.egg-info/PKG-INFO
dumpy.egg-info/SOURCES.txt
dumpy.egg-info/dependency_links.txt
dumpy.egg-info/not-zip-safe
dumpy.egg-info/requires.txt
dumpy.egg-info/top_level.txt
dumpy/tests/__init__.py
dumpy/tests/test_config.py
dumpy/tests/test_types.py