Metadata-Version: 1.1
Name: dumpy
Version: 0.1.2
Summary: Binary protocol parser
Home-page: https://github.com/l04m33/dumpy
Author: Kay Zheng
Author-email: l04m33@gmail.com
License: MIT
Platform: UNKNOWN
Classifier: License :: OSI Approved :: MIT License
Classifier: Programming Language :: Python :: 3
